README
random_variable.py
setup.py
random_variable.egg-info/PKG-INFO
random_variable.egg-info/SOURCES.txt
random_variable.egg-info/dependency_links.txt
random_variable.egg-info/top_level.txt