Metadata-Version: 1.0
Name: random-variable
Version: 0.2
Summary: A library for computing expectation values
Home-page: https://github.com/mdipierro/random_variable
Author: Massimo DiPierro
Author-email: massimo.dipierro@gmail.com
License: BSD
Keywords: expectation values random variables
Platform: UNKNOWN
